assert_matcher/__init__.py
assert_matcher/approx.py
assert_matcher/compare.py
assert_matcher/matchers.py
assert_matcher/plugin.py
assert_matcher-0.9.1.dist-info/licenses/LICENSE
assert_matcher-0.9.1.dist-info/METADATA
assert_matcher-0.9.1.dist-info/WHEEL
assert_matcher-0.9.1.dist-info/entry_points.txt
assert_matcher-0.9.1.dist-info/top_level.txt
assert_matcher-0.9.1.dist-info/RECORD
